[{"name": "guest_id_marketing", "value": "v1%3A175105222492240551", "domain": ".x.com", "path": "/", "expires": 1785612243.860446, "httpOnly": false, "secure": true, "sameSite": "None"}, {"name": "guest_id_ads", "value": "v1%3A175105222492240551", "domain": ".x.com", "path": "/", "expires": 1785612243.860251, "httpOnly": false, "secure": true, "sameSite": "None"}, {"name": "guest_id", "value": "v1%3A175105222492240551", "domain": ".x.com", "path": "/", "expires": 1785612225.000539, "httpOnly": false, "secure": true, "sameSite": "None"}, {"name": "__cf_bm", "value": "FvnL7tHhceFoNBM514cbWDORN2sup0IZnqPipDuKebc-1751052224-1.0.1.1-KBVsjz5GsE40JBSYTSMi.j6LFCQTC3Ooi5n34.PzBrLBpFpvBHPpVGC1_4U7Ejer.wYxitWHLVsN4TRZiTrFd.ssVx.uXD.Hp6dWs0vTz4U", "domain": ".x.com", "path": "/", "expires": 1751054025.000627, "httpOnly": true, "secure": true, "sameSite": "None"}, {"name": "personalization_id", "value": "\"v1_reeCS9Ih8jtP937jEK3rig==\"", "domain": ".x.com", "path": "/", "expires": 1785612225.096424, "httpOnly": false, "secure": true, "sameSite": "None"}, {"name": "gt", "value": "1938679661757624442", "domain": ".x.com", "path": "/", "expires": 1751061225.097167, "httpOnly": false, "secure": true, "sameSite": "Lax"}, {"name": "guest_id_marketing", "value": "v1%3A175105222724154155", "domain": ".twitter.com", "path": "/", "expires": 1785612227.30047, "httpOnly": false, "secure": true, "sameSite": "None"}, {"name": "guest_id_ads", "value": "v1%3A175105222724154155", "domain": ".twitter.com", "path": "/", "expires": 1785612227.300565, "httpOnly": false, "secure": true, "sameSite": "None"}, {"name": "personalization_id", "value": "\"v1_LB3VQPMBxcuR2DV+cvaCtg==\"", "domain": ".twitter.com", "path": "/", "expires": 1785612227.300691, "httpOnly": false, "secure": true, "sameSite": "None"}, {"name": "guest_id", "value": "v1%3A175105222724154155", "domain": ".twitter.com", "path": "/", "expires": 1785612227.30075, "httpOnly": false, "secure": true, "sameSite": "None"}, {"name": "__cf_bm", "value": "I9d3qMvweedTAVNORWlNsvVSxkPRUNker.eX2eTjKUM-1751052227-1.0.1.1-H20n80PdL97j2FBQYrHWvdJvcYZhwlRalW1kP.42jH1niC_LesSZstfBCRbSLV53Hi9qsaTvKSqkfy4owVxYCINmANKg86ZMLSNzkVbAwzg", "domain": ".twitter.com", "path": "/", "expires": 1751054027.300807, "httpOnly": true, "secure": true, "sameSite": "None"}, {"name": "NID", "value": "525=mENgahmuEaUghwF_ippLyCeZEDkoVptVsQ-4l_yzZh3leafe0zSXgcJ0dAsMZ5o33LfDJse7m2_R04vrL_8gPFhE5zaGyJum0yslKKv_uCnEyXM4oHnz4GwIdTNSBia0vSI8JoR2lMV_Q6YAKre8EvFIvIrUvw9rym0ZRF8ZTiwoQNWrAHRWCTbXYZpYkTVAUw", "domain": ".google.com", "path": "/", "expires": 1766863437.667077, "httpOnly": true, "secure": true, "sameSite": "None"}, {"name": "kdt", "value": "V2gyc64D3gSlsPX7yedMiwZTHXmNjyZ9jXzoSPck", "domain": ".x.com", "path": "/", "expires": 1785612240.981409, "httpOnly": true, "secure": true, "sameSite": "Lax"}, {"name": "auth_token", "value": "c9b52b509f47f893f1308e10e65410ed5312894a", "domain": ".x.com", "path": "/", "expires": 1785612240.981751, "httpOnly": true, "secure": true, "sameSite": "None"}, {"name": "ct0", "value": "282693cbeb0e8e4274bbff70a6efcf64eb3ffdaef1cec16a53afb31f713b7be2aff97f98cbf834a8a49ad19e0046b8b30000b12cc284b1669004627b567fe284c8ec2ca0672db377b47f530bd00c0be7", "domain": ".x.com", "path": "/", "expires": 1785612241.46386, "httpOnly": false, "secure": true, "sameSite": "Lax"}, {"name": "att", "value": "1-8bYPXfs3aZhNWIZBNxwZMsWekTLq8vOy1jlMvoIo", "domain": ".x.com", "path": "/", "expires": 1751138641.789129, "httpOnly": true, "secure": true, "sameSite": "None"}, {"name": "lang", "value": "en", "domain": "x.com", "path": "/", "expires": -1, "httpOnly": false, "secure": false, "sameSite": "Lax"}, {"name": "twid", "value": "u%3D1938604487993606144", "domain": ".x.com", "path": "/", "expires": 1782588244.174073, "httpOnly": false, "secure": true, "sameSite": "None"}, {"name": "IDE", "value": "AHWqTUmyj2V46bnm6JQr6K1VP-zEQXZrWedbvti4FfrkLNobVtyMFj0zp72Hor_VgDU", "domain": ".doubleclick.net", "path": "/", "expires": 1785612243.772782, "httpOnly": true, "secure": true, "sameSite": "None"}]